Metadata-Version: 2.4
Name: autoemailwarn
Version: 0.2.0
Summary: A simple SMTP email sender wrapper (QQ Mail default)
Author: Your Name
License: Proprietary
Classifier: Programming Language :: Python :: 3
Classifier: License :: Other/Proprietary License
Classifier: Operating System :: OS Independent
Requires-Python: >=3.8
